setup.py
flask_simple_token/__init__.py
flask_simple_token.egg-info/PKG-INFO
flask_simple_token.egg-info/SOURCES.txt
flask_simple_token.egg-info/dependency_links.txt
flask_simple_token.egg-info/requires.txt
flask_simple_token.egg-info/top_level.txt