Metadata-Version: 1.0
Name: flask-simple-token
Version: 0.0.1
Summary: flask_token generate and verify.
Home-page: UNKNOWN
Author: UNKNOWN
Author-email: UNKNOWN
License: UNKNOWN
Platform: UNKNOWN
